guarneri/__init__.py
guarneri/_typing.py
guarneri/_version.py
guarneri/exceptions.py
guarneri/helpers.py
guarneri/iconfig_example.toml
guarneri/iconfig_example.yaml
guarneri/instrument.py
guarneri/py.typed
guarneri/registry.py
guarneri/tests/__init__.py
guarneri/tests/conftest.py
guarneri/tests/test_helpers.py
guarneri/tests/test_instrument.py
guarneri/tests/test_instrument_registry.py
guarneri-0.5.0.dist-info/licenses/AUTHORS.rst
guarneri-0.5.0.dist-info/licenses/LICENSE
guarneri-0.5.0.dist-info/METADATA
guarneri-0.5.0.dist-info/WHEEL
guarneri-0.5.0.dist-info/top_level.txt
guarneri-0.5.0.dist-info/RECORD
