Metadata-Version: 2.4
Name: guarneri
Version: 0.5.0
Summary: guarneri
Author-email: Mark Wolfman <wolfman@anl.gov>
Project-URL: Homepage, https://github.com/spc-group/guarneri
Classifier: Programming Language :: Python :: 3
Classifier: Operating System :: OS Independent
Classifier: Development Status :: 3 - Alpha
Classifier: Topic :: Scientific/Engineering
Classifier: Topic :: System :: Hardware
Requires-Python: >=3.11
License-File: LICENSE
License-File: AUTHORS.rst
Requires-Dist: ophyd
Requires-Dist: ophyd-async>=0.13.5
Requires-Dist: tomlkit
Requires-Dist: pyyaml
Dynamic: license-file
